pdbpp.py
pdbpp_hijack_pdb.pth
_pdbpp_path_hack/pdb.py
pdbpp-0.12.0.post1.dist-info/licenses/LICENSE.txt
pdbpp_utils/__init__.py
pdbpp_utils/_version.py
pdbpp-0.12.0.post1.dist-info/METADATA
pdbpp-0.12.0.post1.dist-info/WHEEL
pdbpp-0.12.0.post1.dist-info/top_level.txt
pdbpp-0.12.0.post1.dist-info/RECORD
