Metadata-Version: 2.4
Name: pdbpp
Version: 0.12.0.post1
Summary: pdb++, a drop-in replacement for pdb
Author-email: Antonio Cuni <anto.cuni@gmail.com>
Maintainer-email: bretello <bretello@distruzione.org>
License-Expression: BSD-3-Clause
Project-URL: Source Code, https://github.com/bretello/pdbpp
Project-URL: Bug Tracker, https://github.com/bretello/pdbpp/issues
Keywords: pdb,debugger,tab,color,completion
Platform: unix
Platform: linux
Platform: osx
Platform: cygwin
Platform: win32
Classifier: Development Status :: 4 - Beta
Classifier: Environment :: Console
Classifier: Intended Audience :: Developers
Classifier: Operating System :: POSIX
Classifier: Programming Language :: Python :: 3.9
Classifier: Programming Language :: Python :: 3.10
Classifier: Programming Language :: Python :: 3.11
Classifier: Programming Language :: Python :: 3.12
Classifier: Programming Language :: Python :: 3.13
Classifier: Programming Language :: Python :: Implementation :: CPython
Classifier: Programming Language :: Python :: Implementation :: PyPy
Classifier: Programming Language :: Python
Classifier: Topic :: Utilities
Classifier: Topic :: Software Development :: Debuggers
License-File: LICENSE.txt
Requires-Dist: fancycompleter>=0.11.0
Requires-Dist: pygments
Provides-Extra: testing
Requires-Dist: pytest; extra == "testing"
Requires-Dist: pytest-cov; extra == "testing"
Requires-Dist: coverage<7.11.1; extra == "testing"
Requires-Dist: ipython; extra == "testing"
Requires-Dist: pexpect; extra == "testing"
Dynamic: license-file
Dynamic: platform
